tic_tac_toe/TicTacToe.py
tic_tac_toe/__init__.py
tictactoe_abhay-0.0.7.dist-info/LICENSE
tictactoe_abhay-0.0.7.dist-info/METADATA
tictactoe_abhay-0.0.7.dist-info/WHEEL
tictactoe_abhay-0.0.7.dist-info/top_level.txt
tictactoe_abhay-0.0.7.dist-info/RECORD
