Metadata-Version: 2.1
Name: tictactoe-abhay
Version: 0.0.7
Summary: A small package that provide the backend for tictactoe
Home-page: https://github.com/Avashist1998/tictactoe-abhay
Author: Abhay Vashist
Author-email: avashist98@tamu.edu
License: UNKNOWN
Platform: UNKNOWN
Classifier: Programming Language :: Python :: 3
Classifier: License :: OSI Approved :: MIT License
Classifier: Operating System :: OS Independent
Requires-Python: >=3.6
